sysmonitor/__init__.py
sysmonitor/agent/__init__.py
sysmonitor/agent/__main__.py
sysmonitor/agent/auth.py
sysmonitor/agent/configuration.py
sysmonitor/agent/interface.py
sysmonitor/agent/release.py
sysmonitor/agent/utils.py
sysmonitor/agent/interfaces/__init__.py
sysmonitor/agent/interfaces/push.py
sysmonitor/agent/interfaces/rest.py
sysmonitor_agent-2.2.dist-info/LICENSE.txt
sysmonitor_agent-2.2.dist-info/METADATA
sysmonitor_agent-2.2.dist-info/RECORD
sysmonitor_agent-2.2.dist-info/WHEEL
sysmonitor_agent-2.2.dist-info/top_level.txt
