Metadata-Version: 2.1
Name: sysmonitor-agent
Version: 2.2
Summary: System Monitor Agent
Home-page: https://git.hugorodrigues.net/hugorodrigues/sysmonitor-agent
Author: Hugo Rodrigues
Author-email: me@hugorodrigues.net
License: BSD-3-Clause
Platform: UNKNOWN
Classifier: Development Status :: 5 - Production/Stable
Classifier: Environment :: No Input/Output (Daemon)
Classifier: Intended Audience :: System Administrators
Classifier: License :: OSI Approved :: BSD License
Classifier: Programming Language :: Python :: 3 :: Only
Classifier: Operating System :: Unix
Classifier: Topic :: System :: Monitoring
Requires-Python: >=3.5
Requires-Dist: psutil
Requires-Dist: flask
Requires-Dist: requests
